open_sync_board_gui/__init__.py
open_sync_board_gui/components/__init__.py
open_sync_board_gui/components/config_import_dialog.py
open_sync_board_gui/components/event_location_dialog.py
open_sync_board_gui/components/input_config_dialog.py
open_sync_board_gui/components/input_output_config_dialog.py
open_sync_board_gui/components/main_window_v3.py
open_sync_board_gui/components/output_config_dialog.py
open_sync_board_gui/components/source_config_dialog.py
open_sync_board_gui/config/__init__.py
open_sync_board_gui/config/commands_v3.json
open_sync_board_gui/config/hardware_config.py
open_sync_board_gui/config/messages_v3.json
open_sync_board_gui/config/v3.ini
open_sync_board_gui/constants/__init__.py
open_sync_board_gui/constants/board_constants.py
open_sync_board_gui/constants/board_messages.py
open_sync_board_gui/constants/default_devices.py
open_sync_board_gui/constants/settings.py
open_sync_board_gui/dialogs/__init__.py
open_sync_board_gui/dialogs/connection_config_dialog.py
open_sync_board_gui/dialogs/event_location_dialog.py
open_sync_board_gui/dialogs/import_dialog.py
open_sync_board_gui/dialogs/source_config_dialog.py
open_sync_board_gui/logs/.gitignore
open_sync_board_gui/resources.py
open_sync_board_gui/scripts/__init__.py
open_sync_board_gui/scripts/start_gui.py
open_sync_board_gui/start_gui.py
open_sync_board_gui/test.json
open_sync_board_gui/ui/config_import_dialog.ui
open_sync_board_gui/ui/event_location_dialog.ui
open_sync_board_gui/ui/icons/SyncBoard_PCB_V3.png
open_sync_board_gui/ui/icons/SyncBoard_PCB_V3_resized.png
open_sync_board_gui/ui/icons/download.png
open_sync_board_gui/ui/icons/download.svg
open_sync_board_gui/ui/icons/empkins_logo.png
open_sync_board_gui/ui/icons/export-config.png
open_sync_board_gui/ui/icons/folder.png
open_sync_board_gui/ui/icons/folder.svg
open_sync_board_gui/ui/icons/import-config.png
open_sync_board_gui/ui/icons/save.png
open_sync_board_gui/ui/icons/save.svg
open_sync_board_gui/ui/icons/settings.png
open_sync_board_gui-0.1.0.dist-info/LICENSE
open_sync_board_gui-0.1.0.dist-info/METADATA
open_sync_board_gui-0.1.0.dist-info/WHEEL
open_sync_board_gui-0.1.0.dist-info/entry_points.txt
open_sync_board_gui-0.1.0.dist-info/RECORD
