Metadata-Version: 2.1
Name: open-sync-board-gui
Version: 0.1.0
Summary: 
License: MIT
Author: Annika Muecke
Author-email: annika.muecke@fau.de
Requires-Python: >=3.7.1,<3.10
Classifier: License :: OSI Approved :: MIT License
Classifier: Programming Language :: Python :: 3
Classifier: Programming Language :: Python :: 3.8
Classifier: Programming Language :: Python :: 3.9
Requires-Dist: PySide2 (>=5.15.2,<6.0.0)
Requires-Dist: pyserial (>=3.5,<4.0)
